Workbook
Name APORTE: Planilha1!$E$18
Name patrimonio: Planilha1!$E$21
Name qntd_anos: Planilha1!$E$19
Name rendimento_carteira: Planilha1!$E$12
Name tx_mensal: Planilha1!$E$20

Sheet Planilha1
C3: DIO INVESTIMENTOS
C10: CONFIGURAÇÕES
C11: Salário | E11: 5000
C12: Rendimento da Carteira | E12: 0.01
C13: Sugestão de investimento | E13: =E11*30% -> 1500
C17: INVESTIMENTO MENSAL
C18: Quanto investir por mês? | E18: =$E$13 -> 1500
C19: Por quantos anos? | E19: 5
C20: Taxa de rendimento mensal? | E20: 0.01079
C21: Patrimônio acumulado? | E21: =FV(tx_mensal,qntd_anos*12,APORTE)*-1 -> 125665.37
C22: Quanto investir por mês? | E22: =patrimonio*rendimento_carteira -> 1256.6537
B25: 2 | C25: CÉNARIOS | E25: DIVIDENDOS
B26: 5 | C26: 2 ANOS | D26: =FV($E$20,$B25*12,$E$18)*-1 -> 40841.441 | E26: =D26*rendimento_carteira -> 408.41441
B27: 10 | C27: 5 ANOS | D27: =FV($E$20,$B26*12,$E$18)*-1 -> 125665.37 | E27: =D27*rendimento_carteira -> 1256.6537
B28: 20 | C28: 10 ANOS | D28: =FV($E$20,$B27*12,$E$18)*-1 -> 364926.32 | E28: =D28*rendimento_carteira -> 3649.2632
B29: 30 | C29: 20 ANOS | D29: =FV($E$20,$B28*12,$E$18)*-1 -> 1687797.6 | E29: =D29*rendimento_carteira -> 16877.976
C30: 30 ANOS | D30: =FV($E$20,$B29*12,$E$18)*-1 -> 6483254.5 | E30: =D30*rendimento_carteira -> 64832.545
C34: PERFIL | D34: Moderado
C35: Valor investido por mês | D35: =500 -> 500
C38: Tipo de Fii | D38: Percentual Sugerido | E38: Valores
C39: Papel | D39: =VLOOKUP($D$34&"-"&C39,Planilha2!$B:$E,4,FALSE) -> 0.32 | E39: =D39*$D$35 -> 160
C40: Tijolo | D40: =VLOOKUP($D$34&"-"&C40,Planilha2!$B:$E,4,FALSE) -> 0.35 | E40: =D40*$D$35 -> 175
C41: Hibridos | D41: =VLOOKUP($D$34&"-"&C41,Planilha2!$B:$E,4,FALSE) -> 0.08 | E41: =D41*$D$35 -> 40
C42: Desenvolvimento | D42: =VLOOKUP($D$34&"-"&C42,Planilha2!$B:$E,4,FALSE) -> 0.1 | E42: =D42*$D$35 -> 50
C43: FOF's | D43: =VLOOKUP($D$34&"-"&C43,Planilha2!$B:$E,4,FALSE) -> 0.05 | E43: =D43*$D$35 -> 25
C44: Hotelarias | D44: =VLOOKUP($D$34&"-"&C44,Planilha2!$B:$E,4,FALSE) -> 0.1 | E44: =D44*$D$35 -> 50
E45: =SUM(E39:E44) -> 500

Sheet Planilha2
B3: Chave | C3: perfil | D3: tipo de fii | E3: percentual | H3: tipo | I3: %
B4: =C4&"-"&D4 -> Conservador-Papel | C4: Conservador | D4: Papel | E4: 0.3 | H4: Moderado-Tijolo | I4: =VLOOKUP(H4,$B:$E,4,FALSE) -> 0.35
B5: =C5&"-"&D5 -> Conservador-Tijolo | C5: Conservador | D5: Tijolo | E5: 0.5
B6: =C6&"-"&D6 -> Conservador-Hibridos | C6: Conservador | D6: Hibridos | E6: 0.1
B7: =C7&"-"&D7 -> Conservador-Desenvolvimento | C7: Conservador | D7: Desenvolvimento | E7: 0.1
B8: =C8&"-"&D8 -> Conservador-FOF's | C8: Conservador | D8: FOF's | E8: 0
B9: =C9&"-"&D9 -> Conservador-Hotelarias | C9: Conservador | D9: Hotelarias | E9: 0
B10: =C10&"-"&D10 -> Moderado-Papel | C10: Moderado | D10: Papel | E10: 0.32
B11: =C11&"-"&D11 -> Moderado-Tijolo | C11: Moderado | D11: Tijolo | E11: 0.35
B12: =C12&"-"&D12 -> Moderado-Hibridos | C12: Moderado | D12: Hibridos | E12: 0.08
B13: =C13&"-"&D13 -> Moderado-Desenvolvimento | C13: Moderado | D13: Desenvolvimento | E13: 0.1
B14: =C14&"-"&D14 -> Moderado-FOF's | C14: Moderado | D14: FOF's | E14: 0.05
B15: =C15&"-"&D15 -> Moderado-Hotelarias | C15: Moderado | D15: Hotelarias | E15: 0.1
B16: =C16&"-"&D16 -> Agressivo-Papel | C16: Agressivo | D16: Papel | E16: 0.5
... B21: =C21&"-"&D21 -> Agressivo-Hotelarias | C21: Agressivo | D21: Hotelarias | E21: 0.1
